pytest_filedata/__init__.py
pytest_filedata-1.0.0.dist-info/LICENSE
pytest_filedata-1.0.0.dist-info/METADATA
pytest_filedata-1.0.0.dist-info/WHEEL
pytest_filedata-1.0.0.dist-info/RECORD
