Metadata-Version: 2.1
Name: pytest-filedata
Version: 1.0.0
Summary: easily load test data from files
Home-page: https://github.com/20c/pytest-filedata
License: Apache-2.0
Author: 20C
Author-email: code@20c.com
Requires-Python: >=3.8,<4.0
Classifier: Development Status :: 5 - Production/Stable
Classifier: Framework :: Pytest
Classifier: License :: OSI Approved :: Apache Software License
Classifier: Programming Language :: Python :: 3
Classifier: Programming Language :: Python :: 3.8
Classifier: Programming Language :: Python :: 3.9
Classifier: Programming Language :: Python :: 3.10
Classifier: Programming Language :: Python :: 3.11
Classifier: Programming Language :: Python :: 3.12
Classifier: Topic :: Software Development :: Testing
Requires-Dist: decorator (>=4)
Requires-Dist: requests-mock (>=1)
Project-URL: Repository, https://github.com/20c/pytest-filedata
